aiopyql/__init__.py
aiopyql/cache.py
aiopyql/data.py
aiopyql/exceptions.py
aiopyql/mysql_connector.py
aiopyql/postgres_connector.py
aiopyql/sqlite_connector.py
aiopyql/table.py
aiopyql/utilities.py
aiopyql-0.359.dist-info/LICENSE.MD
aiopyql-0.359.dist-info/METADATA
aiopyql-0.359.dist-info/WHEEL
aiopyql-0.359.dist-info/top_level.txt
aiopyql-0.359.dist-info/RECORD
