Metadata-Version: 2.1
Name: aiopyql
Version: 0.359
Summary: A fast and easy-to-use asyncio ORM(Object-relational Mapper) for performing C.R.U.D. ops within RBDMS tables using python
Home-page: https://github.com/codemation/aiopyql
Author: Joshua Jamison
Author-email: joshjamison1@gmail.com
License: UNKNOWN
Platform: UNKNOWN
Classifier: Programming Language :: Python :: 3
Classifier: License :: OSI Approved :: MIT License
Classifier: Operating System :: OS Independent
Requires-Python: >=3.7, <4
Requires-Dist: aiosqlite
Requires-Dist: aiomysql
Requires-Dist: asyncpg
Requires-Dist: cryptography
